smart_prom_next/__init__.py
smart_prom_next/smart_prom_next.py
smart_prom_next-0.0.8.dist-info/LICENSE
smart_prom_next-0.0.8.dist-info/METADATA
smart_prom_next-0.0.8.dist-info/WHEEL
smart_prom_next-0.0.8.dist-info/entry_points.txt
smart_prom_next-0.0.8.dist-info/top_level.txt
smart_prom_next-0.0.8.dist-info/RECORD
