Metadata-Version: 2.1
Name: smart-prom-next
Version: 0.0.8
Summary: S.M.A.R.T. Prometheus Metrics Exporter
Home-page: https://github.com/PhilipMay/smart-prom-next
Author: Philip May
Author-email: philip@may.la
Maintainer: Philip May
Project-URL: Bug Tracker, https://github.com/PhilipMay/smart-prom-next/issues
Project-URL: Source Code, https://github.com/PhilipMay/smart-prom-next
Keywords: prometheus,smart,docker,kubernetes,monitoring,metrics,grafana,hdd,ssd,hard disk
Classifier: Development Status :: 3 - Alpha
Classifier: License :: OSI Approved :: MIT License
Classifier: Programming Language :: Python :: 3.7
Classifier: Programming Language :: Python :: 3.8
Classifier: Programming Language :: Python :: 3.9
Classifier: Programming Language :: Python :: 3.10
Classifier: Programming Language :: Python :: 3.11
Classifier: Programming Language :: Python :: 3 :: Only
Classifier: Topic :: System :: Monitoring
Classifier: Topic :: System :: Systems Administration
Requires-Python: >=3.7
License-File: LICENSE
Requires-Dist: prometheus-client
Provides-Extra: all
Requires-Dist: black ; extra == 'all'
Requires-Dist: mypy ; extra == 'all'
Requires-Dist: pylint ; extra == 'all'
Requires-Dist: mdformat ; extra == 'all'
Requires-Dist: pydocstyle ; extra == 'all'
Requires-Dist: pytest ; extra == 'all'
Requires-Dist: flake8 ; extra == 'all'
Requires-Dist: isort ; extra == 'all'
Requires-Dist: packaging ; extra == 'all'
Requires-Dist: pylintfileheader ; extra == 'all'
Provides-Extra: checking
Requires-Dist: black ; extra == 'checking'
Requires-Dist: flake8 ; extra == 'checking'
Requires-Dist: isort ; extra == 'checking'
Requires-Dist: mdformat ; extra == 'checking'
Requires-Dist: pydocstyle ; extra == 'checking'
Requires-Dist: mypy ; extra == 'checking'
Requires-Dist: pylint ; extra == 'checking'
Requires-Dist: pylintfileheader ; extra == 'checking'
Provides-Extra: testing
Requires-Dist: pytest ; extra == 'testing'
Requires-Dist: packaging ; extra == 'testing'
